vortex/__init__.py
vortex/__main__.py
vortex/cli.py
vortex/colour.py
vortex/constants.py
vortex/logging.py
vortex/main.py
vortex/models.py
vortex/soap.py
vortex/spinner.py
vortex/util.py
vortex/workspace.py
vortex/commands/__init__.py
vortex/commands/clean.py
vortex/commands/clone.py
vortex/commands/code.py
vortex/commands/config.py
vortex/commands/copy.py
vortex/commands/db.py
vortex/commands/delete.py
vortex/commands/docs.py
vortex/commands/execute.py
vortex/commands/export.py
vortex/commands/find.py
vortex/commands/grep.py
vortex/commands/import_.py
vortex/commands/list.py
vortex/commands/log.py
vortex/commands/new.py
vortex/commands/watch.py
vortex/docs/Blackbook.pdf
vortex/lib/puakma-6.0.40.jar
vortex_cli-4.19.1.dist-info/licenses/LICENSE
vortex_cli-4.19.1.dist-info/METADATA
vortex_cli-4.19.1.dist-info/WHEEL
vortex_cli-4.19.1.dist-info/entry_points.txt
vortex_cli-4.19.1.dist-info/top_level.txt
vortex_cli-4.19.1.dist-info/RECORD
