Metadata-Version: 2.4
Name: vortex_cli
Version: 4.19.1
Summary: Vortex CLI
Author-email: Jordan Amos <jordan.amos@gmail.com>
License: MIT License
Keywords: vortex,cli,puakma,tornado
Classifier: Intended Audience :: Developers
Classifier: License :: OSI Approved :: MIT License
Classifier: Natural Language :: English
Classifier: Programming Language :: Python
Classifier: Programming Language :: Python :: 3
Classifier: Programming Language :: Python :: 3 :: Only
Requires-Python: >=3.10
License-File: LICENSE
Requires-Dist: httpx==0.24.1
Requires-Dist: tabulate==0.9.0
Requires-Dist: watchfiles==0.19.0
Dynamic: license-file
